auto_genesis_sdk/__init__.py
auto_genesis_sdk-0.0.3.dist-info/METADATA
auto_genesis_sdk-0.0.3.dist-info/WHEEL
auto_genesis_sdk-0.0.3.dist-info/licenses/LICENSE
auto_genesis_sdk-0.0.3.dist-info/RECORD
