Metadata-Version: 2.4
Name: auto-genesis-sdk
Version: 0.0.3
Summary: A unified Python SDK for seamless integration with Autonomize services, providing telemetry, logging, and tracing capabilities.
Author-email: Muhamed Shahabas C <muhamed@autonomize.ai>
License-File: LICENSE
Requires-Python: >=3.12
Requires-Dist: auto-genesis-telemetry
Provides-Extra: dev
Requires-Dist: black>=23.10.0; extra == 'dev'
Requires-Dist: commitizen>=3.12.0; extra == 'dev'
Requires-Dist: isort>=5.12.0; extra == 'dev'
Requires-Dist: mypy>=1.6.1; extra == 'dev'
Requires-Dist: pre-commit>=3.5.0; extra == 'dev'
Requires-Dist: pytest-cov>=4.1.0; extra == 'dev'
Requires-Dist: pytest>=7.4.3; extra == 'dev'
